quranic_syntax/__init__.py
quranic_syntax/dependency_parsing.py
quranic_syntax/language.py
quranic_syntax/lemmatizer.py
quranic_syntax/postagger.py
quranic_syntax/root.py
quranic_syntax/utils.py
quranic_syntax-1.1.dist-info/LICENSE
quranic_syntax-1.1.dist-info/METADATA
quranic_syntax-1.1.dist-info/WHEEL
quranic_syntax-1.1.dist-info/top_level.txt
quranic_syntax-1.1.dist-info/RECORD
