Metadata-Version: 2.1
Name: quranic-syntax
Version: 1.1
Summary: quarnic syntax
Home-page: https://github.com/language-ml/hadith-quranic_syntax/
License-File: LICENSE
Requires-Dist: spacy
Requires-Dist: pandas
Requires-Dist: numpy
Requires-Dist: openpyxl
